{"id":"0007","horizontalCount":5,"verticalCount":5,"RNGSeed":589,"autoRevealedPieceCount":10,"difficulty":0,"pieces":[{"x":0,"y":0,"status":1,"statusValue":1,"bonus":0,"sourceTextureID":0,"spriteName":"mask_1_8"},{"x":1,"y":0,"status":0,"statusValue":0,"bonus":0,"sourceTextureID":0,"spriteName":"mask_8_7"},{"x":2,"y":0,"status":0,"statusValue":0,"bonus":0,"sourceTextureID":0,"spriteName":"mask_8_7"},{"x":3,"y":0,"status":0,"statusValue":0,"bonus":0,"sourceTextureID":0,"spriteName":"mask_2_1"},{"x":4,"y":0,"status":1,"statusValue":1,"bonus":0,"sourceTextureID":0,"spriteName":"mask_1_3"},{"x":0,"y":1,"status":4,"statusValue":1,"bonus":0,"sourceTextureID":0,"spriteName":"mask_8_4"},{"x":1,"y":1,"status":1,"statusValue":2,"bonus":0,"sourceTextureID":0,"spriteName":"mask_0_8"},{"x":2,"y":1,"status":0,"statusValue":0,"bonus":0,"sourceTextureID":0,"spriteName":"mask_1_0"},{"x":3,"y":1,"status":1,"statusValue":2,"bonus":0,"sourceTextureID":0,"spriteName":"mask_4_7"},{"x":4,"y":1,"status":4,"statusValue":1,"bonus":0,"sourceTextureID":0,"spriteName":"mask_8_3"},{"x":0,"y":2,"status":0,"statusValue":0,"bonus":0,"sourceTextureID":0,"spriteName":"mask_4_0"},{"x":1,"y":2,"status":4,"statusValue":1,"bonus":0,"sourceTextureID":0,"spriteName":"mask_7_0"},{"x":2,"y":2,"status":0,"statusValue":0,"bonus":0,"sourceTextureID":0,"spriteName":"mask_0_0"},{"x":3,"y":2,"status":4,"statusValue":1,"bonus":0,"sourceTextureID":0,"spriteName":"mask_0_6"},{"x":4,"y":2,"status":0,"statusValue":0,"bonus":0,"sourceTextureID":0,"spriteName":"mask_3_2"},{"x":0,"y":3,"status":4,"statusValue":1,"bonus":0,"sourceTextureID":0,"spriteName":"mask_4_0"},{"x":1,"y":3,"status":0,"statusValue":0,"bonus":0,"sourceTextureID":0,"spriteName":"mask_2_6"},{"x":2,"y":3,"status":0,"statusValue":0,"bonus":0,"sourceTextureID":0,"spriteName":"mask_6_0"},{"x":3,"y":3,"status":0,"statusValue":0,"bonus":0,"sourceTextureID":0,"spriteName":"mask_3_0"},{"x":4,"y":3,"status":4,"statusValue":1,"bonus":0,"sourceTextureID":0,"spriteName":"mask_8_1"},{"x":0,"y":4,"status":4,"statusValue":1,"bonus":0,"sourceTextureID":0,"spriteName":"mask_0_5"},{"x":1,"y":4,"status":4,"statusValue":1,"bonus":0,"sourceTextureID":0,"spriteName":"mask_0_1"},{"x":2,"y":4,"status":0,"statusValue":0,"bonus":0,"sourceTextureID":0,"spriteName":"mask_1_6"},{"x":3,"y":4,"status":4,"statusValue":1,"bonus":0,"sourceTextureID":0,"spriteName":"mask_3_8"},{"x":4,"y":4,"status":4,"statusValue":1,"bonus":0,"sourceTextureID":0,"spriteName":"mask_1_5"}],"truckInfos":[],"reward":{"items":[{"type":2,"amount":10}]}}